{
  "sections": {
    "main": {
      "type": "product-hero",
      "settings": {
        "brand_text": "HAGUE PROTECT SOLUTIONS",
        "awards_text": "Professional Grade Formulations",
        "rating_text": "4.9/5 Based on 1,500+ Reviews"
      }
    },
    "features": {
      "type": "corporate-gifting-features",
      "settings": {
        "heading": "Advanced Cleaning Science",
        "subheading": "Specially formulated for premium footwear and delicate fabrics."
      }
    },
    "category": {
      "type": "category",
      "settings": {
        "title": "Shop the Solution Collection"
      }
    }
  },
  "order": [
    "main",
    "features",
    "category"
  ]
}
